README.rst
setup.cfg
setup.py
./__init__.py
./api.py
./bom.py
./carrier.py
./channel.py
./channel.xml
./country.py
./currency.py
./party.py
./payment.py
./product.py
./product.xml
./sale.py
./sale.xml
./tryton.cfg
./wizard.py
./wizard.xml
./tests/__init__.py
./tests/test_base.py
./tests/test_country.py
./tests/test_currency.py
./tests/test_party.py
./tests/test_product.py
./tests/test_sale.py
./tests/test_views.py
./view/category_form.xml
./view/export_inventory_start_form.xml
./view/export_shipment_status_start_form.xml
./view/export_tier_prices_start_form.xml
./view/export_tier_prices_status_form.xml
./view/instance_tree.xml
./view/magento_category_form.xml
./view/magento_category_tree.xml
./view/magento_party_tree.xml
./view/magento_payment_form.xml
./view/magento_payment_tree.xml
./view/magento_product_template_form.xml
./view/magento_product_template_tree.xml
./view/order_state_form.xml
./view/order_state_tree.xml
./view/party_form.xml
./view/price_tier_form.xml
./view/price_tier_tree.xml
./view/product_category_form.xml
./view/product_category_tree.xml
./view/product_channel_listing_form.xml
./view/product_price_tier_form.xml
./view/product_price_tier_tree.xml
./view/sale_channel_form.xml
./view/template_form.xml
./view/template_tree.xml
./view/update_catalog_start_form.xml
./view/wizard_configuration_failure_start_form.xml
./view/wizard_configuration_success_start_form.xml
./view/wizard_export_data_configure_form.xml
./view/wizard_import_carriers_start_form.xml
./view/wizard_import_order_states_start_form.xml
./view/wizard_import_stores_start_form.xml
./view/wizard_import_websites_start_form.xml
./view/wizard_test_connection_start_form.xml
trytond_magento.egg-info/PKG-INFO
trytond_magento.egg-info/SOURCES.txt
trytond_magento.egg-info/dependency_links.txt
trytond_magento.egg-info/entry_points.txt
trytond_magento.egg-info/not-zip-safe
trytond_magento.egg-info/requires.txt
trytond_magento.egg-info/top_level.txt